cfod/__init__.py
cfod/analysis/__init__.py
cfod/analysis/exposure.py
cfod/analysis/filterbank/filterbank.py
cfod/analysis/filterbank/sigproc.py
cfod/analysis/intensity/assemble_chunk.py
cfod/analysis/intensity/chime_intensity.py
cfod/analysis/localization.py
cfod/analysis/waterfall.py
cfod/data/__init__.py
cfod/routines/__init__.py
cfod/routines/catalogs.py
cfod/routines/localizer.py
cfod/routines/msgpack2fil.py
cfod/routines/waterfaller.py
cfod/utilities/__init__.py
cfod/utilities/fetch.py
cfod/utilities/parse.py
cfod-2021.6.4.dist-info/entry_points.txt
cfod-2021.6.4.dist-info/LICENSE
cfod-2021.6.4.dist-info/WHEEL
cfod-2021.6.4.dist-info/METADATA
cfod-2021.6.4.dist-info/RECORD
